odoo/addons/survey_result_mail/README.rst
odoo/addons/survey_result_mail/__init__.py
odoo/addons/survey_result_mail/__manifest__.py
odoo/addons/survey_result_mail/data/mail_template.xml
odoo/addons/survey_result_mail/i18n/it.po
odoo/addons/survey_result_mail/i18n/survey_result_mail.pot
odoo/addons/survey_result_mail/models/__init__.py
odoo/addons/survey_result_mail/models/survey_survey.py
odoo/addons/survey_result_mail/models/survey_user_input.py
odoo/addons/survey_result_mail/readme/CONFIGURE.rst
odoo/addons/survey_result_mail/readme/CONTRIBUTORS.rst
odoo/addons/survey_result_mail/readme/DESCRIPTION.rst
odoo/addons/survey_result_mail/readme/ROADMAP.rst
odoo/addons/survey_result_mail/readme/USAGE.rst
odoo/addons/survey_result_mail/reports/survey_answer_report.xml
odoo/addons/survey_result_mail/static/description/icon.png
odoo/addons/survey_result_mail/static/description/index.html
odoo/addons/survey_result_mail/templates/survey_answer_templates.xml
odoo/addons/survey_result_mail/views/survey_survey_views.xml
odoo13_addon_survey_result_mail-13.0.1.0.1.dev10.dist-info/METADATA
odoo13_addon_survey_result_mail-13.0.1.0.1.dev10.dist-info/WHEEL
odoo13_addon_survey_result_mail-13.0.1.0.1.dev10.dist-info/top_level.txt
odoo13_addon_survey_result_mail-13.0.1.0.1.dev10.dist-info/RECORD
